arborparser/__init__.py
arborparser/build_strategy.py
arborparser/chain.py
arborparser/node.py
arborparser/pattern.py
arborparser/tree.py
arborparser/utils.py
arborparser-0.1.6.dist-info/licenses/LICENSE
arborparser-0.1.6.dist-info/METADATA
arborparser-0.1.6.dist-info/WHEEL
arborparser-0.1.6.dist-info/top_level.txt
arborparser-0.1.6.dist-info/RECORD
