Metadata-Version: 2.4
Name: arborparser
Version: 0.1.6
Summary: ArborParser is a Python library that parses structured text with hierarchical headings into tree representations, enabling customizable pattern recognition and multi-format exports for outlines, reports, and technical documents.
Author-email: Jimmy <jimmy_liang2020@foxmail.com>
License-Expression: MIT
Project-URL: Repository, https://github.com/Jimmy228676/arborparser.git
Project-URL: Issues, https://github.com/Jimmy228676/arborparser/issues
Keywords: tree,parser,arbor,python
Classifier: Development Status :: 4 - Beta
Classifier: Intended Audience :: Developers
Classifier: Programming Language :: Python :: 3
Classifier: Programming Language :: Python :: 3.9
Classifier: Programming Language :: Python :: 3.10
Classifier: Programming Language :: Python :: 3.11
Classifier: Programming Language :: Python :: 3.12
Requires-Python: >=3.9
License-File: LICENSE
Dynamic: license-file
